{
  "ename": 184,
  "cname": "蔡文姬",
  "title": "天籁弦音",
  "occupation": "辅助",
  "attributes": {
    "survival": "5",
    "attack": "1",
    "skill": "8",
    "difficulty": "3"
  },
  "skins": [
    {
      "name": "天籁弦音",
      "id": "0"
    },
    {
      "name": "蔷薇王座",
      "id": "0"
    },
    {
      "name": "奇迹圣诞",
      "id": "37"
    },
    {
      "name": "舞动绿茵",
      "id": "12"
    },
    {
      "name": "繁星吟游",
      "id": "65"
    },
    {
      "name": "花朝如约",
      "id": "15"
    },
    {
      "name": "电玩·兔顽号",
      "id": "12"
    },
    {
      "name": "夏日便利店",
      "id": "132"
    }
  ],
  "skills": [
    {
      "name": "长歌行",
      "cooldownAttributes": "(冷却值：0 消耗：0)",
      "description": "蔡文姬受到伤害时增加持续衰减的35~70%移速，持续2秒，同时每秒回复250~530(+50%法术攻击)生命，持续2秒。该效果每10秒只能触发1次。",
      "tips": "小提示：蔡文姬在逃跑受到伤害的同时，对敌方的任何攻击都会触发被动效果，减速敌人，能更好地进行撤退，小兵和野怪的伤害也能触发这个技能效果，可以利用此效果进行支援gank留人",
      "icon": "https://game.gtimg.cn/images/yxzj/img201606/heroimg/184/18400.png"
    },
    {
      "name": "思无邪",
      "cooldownAttributes": "(冷却值：15/14.4/13.8/13.2/12.6/12 消耗：100)",
      "description": "蔡文姬演奏乐曲，增加40%移速，同时为己方英雄每0.5秒回复60/72/84/96/108/120(+20%法术攻击)点生命，持续3秒，对非英雄单位造成50%效果。",
      "tips": "小提示：在技能范围内的友军能持续回复生命值，并提升移动速度和攻击速度，所以技能施放时尽量靠近多个友军，使得收益最大化",
      "icon": "https://game.gtimg.cn/images/yxzj/img201606/heroimg/184/18410.png"
    },
    {
      "name": "胡笳乐",
      "cooldownAttributes": "(冷却值：10/9.6/9.2/8.8/8.4/8 消耗：70)",
      "description": "蔡文姬发出音波在敌人间弹射，每次弹射造成270/324/378/432/486/540(+48%法术攻击)法术伤害和0.75秒晕眩。每束音波最多弹射6次，同一目标最多受到2次弹射效果，第二次弹射命中时将只造成25%的初始伤害和晕眩时间。",
      "tips": "小提示：这个技能在敌方英雄聚集的时候能发挥巨大的效果，能起到很大的控制作用，在面对追击反手释放时，命中率更高",
      "icon": "https://game.gtimg.cn/images/yxzj/img201606/heroimg/184/18420.png"
    },
    {
      "name": "忘忧曲",
      "cooldownAttributes": "(冷却值：60/55/50 消耗：120)",
      "description": "蔡文姬释放琴音每0.5秒为范围内血量最低的友方英雄回复90/135/180(+45%法术攻击)点生命，持续5秒，同时为其增加200/300/400(+30%法术攻击)点物理和法术防御。",
      "tips": "小提示：团战时，尽量使技能范围包含更多的友军，能降低他们受到的伤害，敌人在大招范围内超过2秒能清空他们的护甲和魔抗，所以对于敌方的坦克英雄来说，这个技能会使他们相当头疼",
      "icon": "https://game.gtimg.cn/images/yxzj/img201606/heroimg/184/18430.png"
    }
  ]
}
