{
  "ename": 549,
  "cname": "心魔六耳",
  "title": "孙悟空命格",
  "occupation": "战士",
  "attributes": {
    "survival": "6",
    "attack": "7",
    "skill": "5",
    "difficulty": "6"
  },
  "skins": [
    {
      "name": "心魔六耳",
      "id": "0"
    }
  ],
  "skills": [
    {
      "name": "心魔凶焰",
      "cooldownAttributes": "(冷却值：0 消耗：0)",
      "description": "心魔六耳普攻(每次命中2点)和基础技能会获得能量(上限60点)，可提升普攻和技能范围(最多25%)使用技能后强化下次普攻为四连击，前三击造成物理伤害(3次视为一次普攻行为)，最后一击造成物理伤害并突进一段距离 使用回城后再次点击可骑乘筋斗云快速返回泉水，过程可被打断 心魔六耳天生拥有20%暴击率和初始150%暴击效果",
      "tips": "小提示：能量积累越多，普攻和技能的范围越大（最多+25%）；使用技能后强化下次普攻为四连击，前三击视为一次普攻可触发暴击和吸血，注意合理安排技能和强化普攻的衔接节奏",
      "icon": "https://game.gtimg.cn/images/yxzj/img201606/heroimg/549/54900.png"
    },
    {
      "name": "前尘断灭",
      "cooldownAttributes": "(冷却值：7.5(-0.3/Lv) 消耗：45)",
      "description": "心魔六耳向指定方向劈击，造成物理伤害(视为普攻行为)，附带晕眩(0.5秒)和陷地(1秒减速)并获得15点能量，每命中一个目标获得回复(非英雄单位减半)",
      "tips": "小提示：前尘断灭视为普攻行为，每次命中可获得15点能量，同时附带晕眩0.5秒和陷地减速1秒；是连招的核心控制手段，尽量优先命中敌方英雄以触发完整控制链",
      "icon": "https://game.gtimg.cn/images/yxzj/img201606/heroimg/549/54912.png"
    },
    {
      "name": "冲霄撼岳",
      "cooldownAttributes": "(冷却值：7.5(-0.3/Lv) 消耗：45)",
      "description": "心魔六耳蓄力浮空(获得能量)，释放后位移至指定目标处劈击，造成物理伤害(视为普攻行为)，附带晕眩(0.5秒)和陷地(1秒减速)并获得15点能量",
      "tips": "小提示：二技能位移可用于赶路，还能卡视野突进打对面一个视野差",
      "icon": "https://game.gtimg.cn/images/yxzj/img201606/heroimg/549/54921.png"
    },
    {
      "name": "十方俱焚",
      "cooldownAttributes": "(冷却值：45(-4.5/Lv) 消耗：140)",
      "description": "心魔六耳化出身外化身，自身进入无法选中状态连续对随机敌人进行四连击，每次造成物理伤害；随后向移动指令方向蓄势冲刺，造成物理伤害(视为普攻行为)，并消耗能量强化最后一击的效果： 消耗30能量：伤害提升25%并造成击退(无控制效果) 消耗60能量：伤害提升50%并造成击退和击飞(持续0.5秒) 蓄势阶段可被控制效果或其他技能打断，返还30%冷却",
      "tips": "小提示：大招蓄力期间心魔六耳进入无法选中状态，可规避敌方关键伤害；消耗60点满能量释放时最后一击额外打出0.5秒击飞，尽量在能量充足时再释放大招以打出最大化爆发",
      "icon": "https://game.gtimg.cn/images/yxzj/img201606/heroimg/549/54930.png"
    }
  ]
}
