{
    "title": "精灵之舞",
    "name": "艾琳",
    "attributes": {},
    "skills": [
        {
            "name": "精灵舞步",
            "info": "(冷却值：0 消耗：0)",
            "description": "艾琳普攻造成(+100%物理攻击)(+20%法术攻击)物理伤害，并获得能量。能量充盈后艾琳消耗能量急速飞行，每100点法术攻击可以提升25~50点移速(最多675)。能量充盈后艾琳获得一层月桂印记和强化普攻，对路径上的目标造成70(+120%物理攻击)(+30%法术攻击)物理伤害。 艾琳的穿透/吸血为全能穿透/吸血，取物理穿透/吸血和法术穿透/吸血的较大者。",
            "tips": "小提示：能量满后消耗完毕才能获取新的能量，注意攻击和移动节奏避免无法获取新的能量"
        },
        {
            "name": "叶舞·致意",
            "info": "(冷却值：7.5/7.2/6.9/6.6/6.3/6 消耗：0)",
            "description": "艾琳射出一束月桂叶，对命中的目标造成510/612/714/816/918/1020(+115%额外攻击)(+100%法术攻击)法术伤害，并叠加一层月桂印记，命中敌方英雄或飞行到最远处后展开成环，对触碰的敌人造成175/210/245/280/315/350(+40%物理攻击)(+37%法术攻击)法术伤害和15/18/21/24/27/30%减速，持续1秒。每100点法术攻击减少0.1秒技能冷却，最多减少1.5秒。",
            "tips": "小提示：命中敌方英雄单位或到达最远处才能展开成圆环。大招期间无法使用。"
        },
        {
            "name": "旋舞·轻语",
            "info": "(冷却值：10/9.6/9.2/8.8/8.4/8 消耗：0)",
            "description": "艾琳受到黄金森林的祝福，立即回满能量(获得一层月桂印记并强化普攻)，同时再获得一层月桂印记。艾琳获得免疫减速并增加20/24/28/32/36/40%攻速，持续3秒。",
            "tips": "小提示：期间免疫减速，是用来追击和撤退的手段。且释放时额外增加一层月桂印记，多多释放2技能才能快速叠起大招层数。"
        },
        {
            "name": "月桂之舞·盛放",
            "info": "(冷却值：20/17.5/15 消耗：0)",
            "description": "艾琳能量满后会叠加一层月桂印记。当月桂印记达到6层时【月桂之舞·盛放】解锁，印记叠加上限为12/15/18层。技能开启时，艾琳增加10/15/20%移速，不断消耗印记发出月桂飞叶，对范围内血量最低的目标造成72/108/114(+35%物理攻击)(+25%法术攻击)法术伤害，并减少【旋舞·轻语】0.2秒的冷却时间。再次点击可以提前关闭技能，每3枚飞叶视为1次普攻行为。",
            "tips": "小提示：大招只能攻击最近的单位，注意走位。且期间增加移速，可以提前开启追击敌人或者撤退。"
        }
    ],
    "recommended_builds": {
        "winning_build": [
            "1425",
            "1129",
            "1728",
            "1232",
            "1222",
            "1231"
        ],
        "losing_build": [
            "1425",
            "1129",
            "1728",
            "1232",
            "1222",
            "1223"
        ]
    },
    "inscriptions": [
        "1510",
        "2503",
        "3515"
    ],
    "relations": {
        "best_partners": [
            {
                "hero_id": "168",
                "reason": "牛魔可以提供控制和坦度，为艾琳创造输出空间。且被动可以提高艾琳的生存能力。"
            },
            {
                "hero_id": "505",
                "reason": "瑶可以提高艾琳的生存能力"
            }
        ],
        "restrained_by": [
            {
                "hero_id": "508",
                "reason": "伽罗的长射程使艾琳在对线中无法应对，且艾琳的灵活性受到伽罗减速的克制。"
            },
            {
                "hero_id": "169",
                "reason": "后羿可以先手控制艾琳，且站桩输出能力高于艾琳。"
            }
        ],
        "restrains_who": [
            {
                "hero_id": "132",
                "reason": "艾琳的灵活性使马可的技能很难命中"
            },
            {
                "hero_id": "174",
                "reason": "艾琳全法术伤害使虞姬的2技能无法免疫"
            }
        ]
    }
}