{
    "title": "叛逆吟游",
    "name": "高渐离",
    "attributes": {},
    "skills": [
        {
            "name": "哀歌",
            "info": "(冷却值：0 消耗：0)",
            "description": "高渐离的普攻和技能可视作弹奏，每三次弹奏后的下次普攻会强化为能量和弦，对路径上的敌人造成280(+80%法术攻击)法术伤害。",
            "tips": "小提示：能量和弦具有穿透效果，同时拥有物理与法术加成.这个效果不管在前后期都是不错的消耗方式"
        },
        {
            "name": "狂歌",
            "info": "(冷却值：8/7.8/7.6/7.4/7.2/7 消耗：55)",
            "description": "高渐离弹奏出音符，对范围内至多2名敌人造成350/410/470/530/590/650(+47%法术攻击)法术伤害。音符命中敌人后会向附近的敌人进行弹射，音符至多弹射2次。当多个音符命中同一目标时，后续音符只造成30%伤害。",
            "tips": "小提示：技能可同时攻击两个敌方单位，并且施法范围较大，对线或团战前都可以用来消耗敌人，前期伤害也是较为可观的."
        },
        {
            "name": "离歌",
            "info": "(冷却值：10/9.6/9.2/8.8/8.4/8 消耗：70)",
            "description": "高渐离朝指定方向位移，同时震慑琴弦对附近敌人造成450/540/630/720/810/900(+60%法术攻击)法术伤害和15/18/21/24/27/30%减速，持续2秒。每命中一个英雄回复100/120/140/160/180/200(+15%法术攻击)点生命，非英雄单位减半。位移期间获得10/12/14/16/18/20%减伤并且免疫减速。位移期间释放【狂歌】可以进行二次位移。",
            "tips": "小提示：AOE技能，造成伤害并减速，能留住敌人，配合大招使用效果更佳.但需注意，此技能范围较小，注意与敌军距离，靠近后再释放"
        },
        {
            "name": "魔音贯耳",
            "info": "(冷却值：45/40/35 消耗：140)",
            "description": "高渐离激情演奏，持续5秒，每0.5秒弹奏一下，造成200/300/400(+20%法术攻击)法术伤害。演奏开始时高渐离逐渐增加50%移速，3秒内随时间衰减。演奏持续期间附近有敌方英雄获得10%减伤，此外每多一名敌方英雄，额外提供5%减伤。",
            "tips": "小提示：持续性的AOE输出加上免伤效果和移动速度加成，这个技能在后期有着高额的法术伤害和极强的机动性，是非常棒的团战切后排的技能."
        }
    ],
    "recommended_builds": {
        "winning_build": [
            "1422",
            "1240",
            "1235",
            "1336",
            "1231",
            "1232"
        ],
        "losing_build": [
            "1422",
            "1240",
            "1235",
            "1336",
            "1239",
            "1231"
        ]
    },
    "inscriptions": [
        "1514",
        "3515",
        "2503"
    ],
    "relations": {
        "best_partners": [
            {
                "hero_id": "120",
                "reason": "白起：白起钩子和嘲讽技能能够让对方全部聚集到一起，高渐离这时候开大进场能够打出恐怖的伤害，这一套往往能够击杀对面多人，取得巨大的优势。"
            },
            {
                "hero_id": "113",
                "reason": "庄周：高渐离最怕开大进场时候被对面控住，打不出输出，庄周可以很好的避免这个问题，大招的解控和免控可以有效提升高渐离的输出环境，庄周大招免伤配合高渐离大招时使用技能的免伤效果也可以让高渐离生存能力满值。"
            }
        ],
        "restrained_by": [
            {
                "hero_id": "150",
                "reason": "刺客的爆发输出很容易切入击杀高渐离"
            },
            {
                "hero_id": "154",
                "reason": "花木兰的超高爆发输出能力能快速击杀走位不慎的高渐离"
            }
        ],
        "restrains_who": [
            {
                "hero_id": "192",
                "reason": "黄忠：黄忠是站桩输出型英雄，没有任何位移技能，而且开大时不能移动，虽然增加了一定的魔抗，但是对于穿透和爆发比较高的高渐离来说效果甚微，高渐离开大后使用技能靠近黄忠后受到的伤害也比较少，可以轻松秒掉黄忠。"
            },
            {
                "hero_id": "141",
                "reason": "貂蝉：高渐离有非常强的瞬间爆发输出能力，可以利用大招状态下的免伤效果提升自己的生存环境，配合被动伤害效果可以在短时间内成为一个恐怖的输出点。貂蝉更偏向于持续输出，利用位移和回复效果维持生存的同时打出高额的伤害。在对线或者团战的时候，貂蝉很难和高渐离对抗，经常都会被高渐离一套带走。"
            }
        ]
    }
}