{
    "title": "万物有灵",
    "name": "鬼谷子",
    "attributes": {},
    "skills": [
        {
            "name": "纵横兵法",
            "info": "(冷却值：0 消耗：0)",
            "description": "鬼谷子脱离敌方视野3秒后，可强化下一次普攻，对范围目标造成300~600(+55%法术攻击)法术伤害和25~50%减速，持续1.5秒。如果使用强化攻击时，鬼谷子不处于敌方视野，则【纵横兵法】的冷却将会增加至10秒。",
            "tips": "小提示：这个技能能帮助鬼谷子去游走时能很好的减速留下敌人，需要配合队友输出将敌人击杀"
        },
        {
            "name": "先知·神隐",
            "info": "(冷却值：10 消耗：60)",
            "description": "用玄微子包裹自身进入伪装状态，持续4秒，期间增加40%移速，并对触碰到的每个敌人造成450/540/630/720/810/900(+60%法术攻击)法术伤害，同时降低该敌人25/28/31/34/37/40%的物理和法术防御，持续4秒，每个敌人最多触发1次。伪装效果会在鬼谷子用其他方式伤害敌人时消失。",
            "tips": "小提示：这个技能降低敌人护甲和魔抗，能很好的提升我方输出英雄打前排的能力"
        },
        {
            "name": "万物有灵",
            "info": "(冷却值：10/9.6/9.2/8.8/8.4/8 消耗：60)",
            "description": "召唤大量玄微子在自身周围聚集，对范围内敌人每0.5秒造成100/120/140/160/180/200(+15%法术攻击)法术伤害，持续2秒，2秒后将范围内敌人拉扯到鬼谷子身旁并将其晕眩1秒同时造成400(+60%法术攻击)法术伤害。如果该伤害命中敌方英雄，鬼谷子和范围内的队友将获得500/600/700/800/900/1000(+100%法术攻击)点护盾。",
            "tips": "小提示：这个技能是鬼谷子作为辅助的核心控制技能，需要把握技能施放时机，和合理的走位，才能使得它能控制更多的敌人。同时，给附近的队友加护盾，让队友抵消一些伤害"
        },
        {
            "name": "先知·雾隐",
            "info": "(冷却值：35/30/25 消耗：120)",
            "description": "命令玄微子包裹自身和1500范围内的队友，1秒后进入伪装状态，期间鬼谷子和队友将增加30%移速，持续4秒，同时获取距离自身最近的敌方英雄视野。伪装状态下，如果使用普攻、技能或对敌方造成负面效果时会立即解除伪装状态。",
            "tips": "小提示：这个技能是鬼谷子的核心功能，开启大招，附近友军群体隐身，能够在战术上得到很好的施展，可以群体隐身抱团进攻突袭，亦可用于保护友军进行撤退"
        }
    ],
    "recommended_builds": {
        "winning_build": [
            "1426",
            "1724",
            "1336",
            "1335",
            "1332",
            "1337"
        ],
        "losing_build": [
            "1722",
            "1426",
            "1336",
            "1335",
            "1333",
            "1337"
        ]
    },
    "inscriptions": [
        "1514",
        "3511",
        "2520"
    ],
    "relations": {
        "best_partners": [
            {
                "hero_id": "115",
                "reason": "高渐离：推荐的原因是高渐离和鬼谷子的技能搭配爆发配合满分，鬼谷子游走或者团战时，使用1技能可以添加减抗性效果，3技能可以获得加速和群体隐身效果，2技能可以把敌人拉在一起并眩晕。和高渐离配合时用3技能隐身迅速贴近被1技能减少抗性的敌人，利用2技能硬控晕住的敌人，可以让高渐离有良好的输出环境。"
            },
            {
                "hero_id": "131",
                "reason": "李白：鬼谷子和李白可以产生很好的联动效果，李白2技能减伤后大招可以伤害爆炸，鬼谷子的1技能可以减少敌方抗性，配合李白的2技能大招会让伤害最大化，大招隐身技能也可以让李白的行踪难以被掌控。"
            }
        ],
        "restrained_by": [
            {
                "hero_id": "132",
                "reason": "机动性高的英雄不太容易被鬼谷子抓住"
            },
            {
                "hero_id": "173",
                "reason": "李元芳能侦测到鬼谷子的大概位置"
            }
        ],
        "restrains_who": [
            {
                "hero_id": "152",
                "reason": "王昭君：鬼谷子1技能加移速特别快，很容易躲掉王昭君最核心的2技能，鬼谷子也可以利用2技能控制破解王昭君的大招，所以鬼谷子相对克制王昭君，只要避免不被王昭君2技能大招秒掉可以轻松和王昭君对线，鬼谷子的持续输出能力也比较强，可以轻松应对王昭君。"
            },
            {
                "hero_id": "153",
                "reason": "兰陵王：兰陵王的核心玩法是隐身靠近敌方核心输出位，寻找时机切死敌方后排，而鬼谷子大招开启时会触发反隐效果，可以轻松发现兰陵王的身位，配合队友利用2技能控制1技能的减少抗性轻松秒掉兰陵王。"
            }
        ]
    }
}